django_tokko_rpc/__init__.py
django_tokko_rpc/apps.py
django_tokko_rpc/management/__init__.py
django_tokko_rpc/management/commands/__init__.py
django_tokko_rpc/management/commands/run_rpc_server.py
django_tokko_rpc-0.0.6.dist-info/METADATA
django_tokko_rpc-0.0.6.dist-info/WHEEL
django_tokko_rpc-0.0.6.dist-info/top_level.txt
django_tokko_rpc-0.0.6.dist-info/RECORD
